setup.py
Resize_CMD.egg-info/PKG-INFO
Resize_CMD.egg-info/SOURCES.txt
Resize_CMD.egg-info/dependency_links.txt
Resize_CMD.egg-info/entry_points.txt
Resize_CMD.egg-info/requires.txt
Resize_CMD.egg-info/top_level.txt
resize_cmd/__init__.py
resize_cmd/commands.py
resize_cmd/functions.py