Metadata-Version: 1.0
Name: Resize-CMD
Version: 1.0
Summary: Resize images with a command
Home-page: https://justmaffie.nl
Author: JustMaffie
Author-email: jori@justmaffie.nl
License: AGPL
Platform: UNKNOWN
